pyzfn/__init__.py
pyzfn/calc_modes.py
pyzfn/equations.py
pyzfn/ispec.py
pyzfn/ovf.py
pyzfn/pyzfn.py
pyzfn/snapshot.py
pyzfn/utils.py
pyzfn-1.0.5.dist-info/licenses/LICENSE
tests/__init__.py
tests/conftest.py
tests/test_calc_modes.py
tests/test_equations.py
tests/test_ispec.py
tests/test_ovf.py
tests/test_pyzfn.py
tests/test_snapshot.py
tests/test_utils.py
pyzfn-1.0.5.dist-info/METADATA
pyzfn-1.0.5.dist-info/WHEEL
pyzfn-1.0.5.dist-info/top_level.txt
pyzfn-1.0.5.dist-info/RECORD
