Metadata-Version: 2.4
Name: pyzfn
Version: 1.0.5
Summary: micromagnetic post processing library
Author-email: Mathieu Moalic <matmoa@amu.edu.pl>, Mateusz Zelent <mateusz.zelent@amu.edu.pl>
License-Expression: GPL-3.0-or-later
Classifier: Programming Language :: Python :: 3
Classifier: Programming Language :: Python :: 3 :: Only
Requires-Python: >=3.11
License-File: LICENSE
Requires-Dist: matplotlib~=3.10
Requires-Dist: numpy~=2.2
Requires-Dist: zarr~=3.0.8
Requires-Dist: typing_extensions~=4.13.2
Requires-Dist: crc32c~=2.7.1
Requires-Dist: rich~=14.0.0
Dynamic: license-file
